Metadata-Version: 1.0
Name: daria-pypi-lib
Version: 0.1.0
Summary: Super unuseful library- Hello
Home-page: UNKNOWN
Author: Daria Dudek-Wojtuń
Author-email: UNKNOWN
License: UNKNOWN
Platform: UNKNOWN
